examplepro_3/__init__.py
examplepro_3/__main__.py
examplepro_3-1.0.1.dist-info/LICENSE
examplepro_3-1.0.1.dist-info/METADATA
examplepro_3-1.0.1.dist-info/WHEEL
examplepro_3-1.0.1.dist-info/top_level.txt
examplepro_3-1.0.1.dist-info/RECORD
