Metadata-Version: 2.1
Name: examplepro-3
Version: 1.0.1
Summary: only a test 
Author: Dominik Wuttke
License: Apache License
License-File: LICENSE
